unboil_fastapi_query/__init__.py
unboil_fastapi_query/sqlalchemy.py
unboil_fastapi_query-0.1.2.dist-info/METADATA
unboil_fastapi_query-0.1.2.dist-info/WHEEL
unboil_fastapi_query-0.1.2.dist-info/licenses/LICENSE
unboil_fastapi_query-0.1.2.dist-info/RECORD
