Metadata-Version: 2.4
Name: unboil-fastapi-query
Version: 0.1.2
Summary: A library providing tools for easily querying a FastAPI application.
Project-URL: homepage, https://github.com/eyueldk/unboil-fastapi-query
Project-URL: repository, https://github.com/eyueldk/unboil-fastapi-query
Author: eyueldk
License: MIT
License-File: LICENSE
Keywords: fastapi,filter,pagination,query,sorting,sqlalchemy,unboil
Classifier: License :: OSI Approved :: MIT License
Classifier: Operating System :: OS Independent
Classifier: Programming Language :: Python :: 3
Classifier: Programming Language :: Python :: 3.9
Requires-Python: >=3.9
Requires-Dist: fastapi>=0.115.0
Requires-Dist: sqlalchemy>=2.0.0
